top_k_models/__init__.py
top_k_models/classification.py
top_k_models/solar_radiation_project_example1.py
top_k_models-0.0.2.dist-info/LICENSE
top_k_models-0.0.2.dist-info/METADATA
top_k_models-0.0.2.dist-info/WHEEL
top_k_models-0.0.2.dist-info/top_level.txt
top_k_models-0.0.2.dist-info/RECORD
