Metadata-Version: 2.1
Name: top-k-models
Version: 0.0.2
Summary: Top-k classification and model selector
Home-page: https://github.com/priscilla-chk/top_k_models
Author: Priscilla Chauke
Author-email: priscilla.chk@gmail.com
License: GNU General Public License v3.0
Platform: UNKNOWN
Requires-Python: >=3.6
Requires-Dist: numpy
Requires-Dist: pandas
Requires-Dist: scikit-learn
